setup.py
bin/ys
youtube_streamer.egg-info/PKG-INFO
youtube_streamer.egg-info/SOURCES.txt
youtube_streamer.egg-info/dependency_links.txt
youtube_streamer.egg-info/requires.txt
youtube_streamer.egg-info/top_level.txt
ys/__init__.py