Metadata-Version: 1.1
Name: youtube-streamer
Version: 1.0.1
Summary: Stream youtube videos
Home-page: https://github.com/dushyantRathore/Youtube-Streamer
Author: Dushyant Rathore
Author-email: dushyant.bgs@gmail.com
License: MIT
Keywords: Youtube video streamer
Platform: UNKNOWN
Classifier: Development Status :: 3 - Alpha
Classifier: Environment :: Console
Classifier: Intended Audience :: Developers
Classifier: Intended Audience :: Information Technology
Classifier: Natural Language :: English
Classifier: Topic :: Software Development :: Build Tools
Classifier: License :: OSI Approved :: MIT License
Classifier: Programming Language :: Python :: 2
Classifier: Programming Language :: Python :: 2.6
Classifier: Programming Language :: Python :: 2.7
